odoo/addons/sale_order_product_recommendation_product_sold_by_delivery_week/README.rst
odoo/addons/sale_order_product_recommendation_product_sold_by_delivery_week/__init__.py
odoo/addons/sale_order_product_recommendation_product_sold_by_delivery_week/__manifest__.py
odoo/addons/sale_order_product_recommendation_product_sold_by_delivery_week/i18n/es.po
odoo/addons/sale_order_product_recommendation_product_sold_by_delivery_week/i18n/sale_order_product_recommendation_product_sold_by_delivery_week.pot
odoo/addons/sale_order_product_recommendation_product_sold_by_delivery_week/readme/CONTRIBUTORS.rst
odoo/addons/sale_order_product_recommendation_product_sold_by_delivery_week/readme/DESCRIPTION.rst
odoo/addons/sale_order_product_recommendation_product_sold_by_delivery_week/static/description/icon.png
odoo/addons/sale_order_product_recommendation_product_sold_by_delivery_week/static/description/index.html
odoo/addons/sale_order_product_recommendation_product_sold_by_delivery_week/wizard/__init__.py
odoo/addons/sale_order_product_recommendation_product_sold_by_delivery_week/wizard/sale_order_recommendation.py
odoo/addons/sale_order_product_recommendation_product_sold_by_delivery_week/wizard/sale_order_recommendation_view.xml
odoo13_addon_sale_order_product_recommendation_product_sold_by_delivery_week-13.0.1.0.1.dist-info/METADATA
odoo13_addon_sale_order_product_recommendation_product_sold_by_delivery_week-13.0.1.0.1.dist-info/WHEEL
odoo13_addon_sale_order_product_recommendation_product_sold_by_delivery_week-13.0.1.0.1.dist-info/top_level.txt
odoo13_addon_sale_order_product_recommendation_product_sold_by_delivery_week-13.0.1.0.1.dist-info/RECORD
